rcpchgrowth/__init__.py
rcpchgrowth/age_advice_strings.py
rcpchgrowth/bmi_functions.py
rcpchgrowth/bone_age.py
rcpchgrowth/cdc.py
rcpchgrowth/centile_bands.py
rcpchgrowth/chart_functions.py
rcpchgrowth/date_calculations.py
rcpchgrowth/dynamic_growth.py
rcpchgrowth/fictional_child.py
rcpchgrowth/global_functions.py
rcpchgrowth/measurement.py
rcpchgrowth/mid_parental_height.py
rcpchgrowth/trisomy_21.py
rcpchgrowth/trisomy_21_aap.py
rcpchgrowth/turner.py
rcpchgrowth/uk_who.py
rcpchgrowth/who.py
rcpchgrowth/data_tables/bayley-pineau.pdf
rcpchgrowth/data_tables/cdc.json
rcpchgrowth/data_tables/cdc2-20.json
rcpchgrowth/data_tables/cdc_infants.json
rcpchgrowth/data_tables/trisomy_21.json
rcpchgrowth/data_tables/trisomy_21_aap_children.json
rcpchgrowth/data_tables/trisomy_21_aap_infants.json
rcpchgrowth/data_tables/turner.json
rcpchgrowth/data_tables/uk90_child.json
rcpchgrowth/data_tables/uk90_preterm.json
rcpchgrowth/data_tables/uk90_term.json
rcpchgrowth/data_tables/who_2007_children.json
rcpchgrowth/data_tables/who_children.json
rcpchgrowth/data_tables/who_infants.json
rcpchgrowth/data_tables/aap_resources/AAP [0 -  36 months]/hc_age_boys_aap_0-36M.xlsx
rcpchgrowth/data_tables/aap_resources/AAP [0 -  36 months]/hc_age_girls_aap_0-36M.xlsx
rcpchgrowth/data_tables/aap_resources/AAP [0 -  36 months]/ht_age_boys_aap_0-36M.xlsx
rcpchgrowth/data_tables/aap_resources/AAP [0 -  36 months]/ht_age_girls_aap_0-36M.xlsx
rcpchgrowth/data_tables/aap_resources/AAP [0 -  36 months]/wt_age_boys_aap_0-36M.xlsx
rcpchgrowth/data_tables/aap_resources/AAP [0 -  36 months]/wt_age_girls_aap_0-36M.xlsx
rcpchgrowth/data_tables/aap_resources/AAP [0 -  36 months]/wt_ht_boys_aap_0-36M.xlsx
rcpchgrowth/data_tables/aap_resources/AAP [0 -  36 months]/wt_ht_girls_aap_0-36M.xlsx
rcpchgrowth/data_tables/aap_resources/AAP [2 -  20 years]/bmi_age_boys_aap_2-20Y.xlsx
rcpchgrowth/data_tables/aap_resources/AAP [2 -  20 years]/bmi_age_girls_aap_2-20Y.xlsx
rcpchgrowth-4.4.0.dist-info/licenses/LICENSE
rcpchgrowth-4.4.0.dist-info/METADATA
rcpchgrowth-4.4.0.dist-info/WHEEL
rcpchgrowth-4.4.0.dist-info/top_level.txt
rcpchgrowth-4.4.0.dist-info/RECORD
