Metadata-Version: 2.4
Name: rcpchgrowth
Version: 4.4.0
Summary: SDS and Centile calculations for UK Growth Data
Author-email: RCPCH Incubator <incubator@rcpch.ac.uk>
Maintainer-email: RCPCH Incubator <incubator@rcpch.ac.uk>
License-Expression: AGPL-3.0-or-later
Project-URL: Homepage, https://github.com/rcpch/rcpchgrowth-python
Project-URL: Bug Reports, https://github.com/rcpch/rcpchgrowth-python/issues
Project-URL: API management, https://dev.rcpch.ac.uk
Project-URL: Documentation, https://growth.rcpch.ac.uk/products/python-library/
Keywords: growth charts,anthropometry,SDS,centile,UK-WHO,UK90,Trisomy 21,Turner,CDC
Classifier: Development Status :: 5 - Production/Stable
Classifier: Programming Language :: Python :: 3 :: Only
Classifier: Programming Language :: Python :: 3.9
Classifier: Programming Language :: Python :: 3.10
Classifier: Programming Language :: Python :: 3.11
Classifier: Programming Language :: Python :: 3.12
Classifier: Topic :: Scientific/Engineering :: Medical Science Apps.
Requires-Python: >=3.8
License-File: LICENSE
Requires-Dist: python-dateutil
Requires-Dist: scipy
Provides-Extra: notebook
Requires-Dist: pandas>=1.5; extra == "notebook"
Requires-Dist: matplotlib>=3.7; extra == "notebook"
Requires-Dist: jupyterlab; extra == "notebook"
Requires-Dist: ipykernel; extra == "notebook"
Dynamic: license-file
